{
  "urn" : "local:Benat_Egidazu:esa.aries.sandbox:esa_weed_small_areas_within_polygons",
  "version" : "0.0.1",
  "adapterType" : "wfs",
  "localPath" : "esa.aries.sandbox/resources/esa_weed_small_areas_within_polygons",
  "geometry" : "#s2(54){bbox=[-75.28277587890625 106.4932632446289 -34.66094970703125 70.79414367675781],proj=EPSG:4326}",
  "projectName" : "esa.aries.sandbox",
  "localName" : "esa_weed_small_areas_within_polygons",
  "type" : "OBJECT",
  "resourceTimestamp" : 1777036206570,
  "metadata" : {
    "im:keywords" : "features,small_areas_within_polygons",
    "dc:title" : "small_areas_within_polygons"
  },
  "parameters" : {
    "serviceUrl" : "https://integration.integratedmodelling.org/geoserver/esa_weed/ows",
    "wfsVersion" : "1.0.0",
    "wfsIdentifier" : "esa_weed:small_areas_within_polygons"
  },
  "localPaths" : [ ],
  "history" : [ ],
  "notifications" : [ ],
  "attributes" : [ {
    "name" : "parent_id",
    "type" : "NUMBER",
    "key" : false,
    "optional" : true,
    "exampleValue" : null,
    "index" : 0
  }, {
    "name" : "val_r_cnt",
    "type" : "NUMBER",
    "key" : false,
    "optional" : true,
    "exampleValue" : null,
    "index" : 0
  }, {
    "name" : "sample_id",
    "type" : "NUMBER",
    "key" : false,
    "optional" : true,
    "exampleValue" : null,
    "index" : 0
  }, {
    "name" : "cntry_cod",
    "type" : "TEXT",
    "key" : false,
    "optional" : true,
    "exampleValue" : null,
    "index" : 0
  }, {
    "name" : "tidal_int",
    "type" : "BOOLEAN",
    "key" : false,
    "optional" : true,
    "exampleValue" : null,
    "index" : 0
  }, {
    "name" : "recur",
    "type" : "BOOLEAN",
    "key" : false,
    "optional" : true,
    "exampleValue" : null,
    "index" : 0
  }, {
    "name" : "periodic",
    "type" : "BOOLEAN",
    "key" : false,
    "optional" : true,
    "exampleValue" : null,
    "index" : 0
  }, {
    "name" : "ann_npp",
    "type" : "BOOLEAN",
    "key" : false,
    "optional" : true,
    "exampleValue" : null,
    "index" : 0
  }, {
    "name" : "spec_leaf",
    "type" : "BOOLEAN",
    "key" : false,
    "optional" : true,
    "exampleValue" : null,
    "index" : 0
  }, {
    "name" : "leaf_size",
    "type" : "BOOLEAN",
    "key" : false,
    "optional" : true,
    "exampleValue" : null,
    "index" : 0
  }, {
    "name" : "cc_col",
    "type" : "BOOLEAN",
    "key" : false,
    "optional" : true,
    "exampleValue" : null,
    "index" : 0
  }, {
    "name" : "cc_vnm",
    "type" : "BOOLEAN",
    "key" : false,
    "optional" : true,
    "exampleValue" : null,
    "index" : 0
  }, {
    "name" : "cc_cze",
    "type" : "BOOLEAN",
    "key" : false,
    "optional" : true,
    "exampleValue" : null,
    "index" : 0
  }, {
    "name" : "cc_zaf",
    "type" : "BOOLEAN",
    "key" : false,
    "optional" : true,
    "exampleValue" : null,
    "index" : 0
  }, {
    "name" : "cc_nor",
    "type" : "BOOLEAN",
    "key" : false,
    "optional" : true,
    "exampleValue" : null,
    "index" : 0
  }, {
    "name" : "cc_grc",
    "type" : "BOOLEAN",
    "key" : false,
    "optional" : true,
    "exampleValue" : null,
    "index" : 0
  }, {
    "name" : "ch_vnm",
    "type" : "BOOLEAN",
    "key" : false,
    "optional" : true,
    "exampleValue" : null,
    "index" : 0
  }, {
    "name" : "ch_grc",
    "type" : "BOOLEAN",
    "key" : false,
    "optional" : true,
    "exampleValue" : null,
    "index" : 0
  }, {
    "name" : "ch_cze",
    "type" : "BOOLEAN",
    "key" : false,
    "optional" : true,
    "exampleValue" : null,
    "index" : 0
  }, {
    "name" : "ch_nor",
    "type" : "BOOLEAN",
    "key" : false,
    "optional" : true,
    "exampleValue" : null,
    "index" : 0
  }, {
    "name" : "ch_col",
    "type" : "BOOLEAN",
    "key" : false,
    "optional" : true,
    "exampleValue" : null,
    "index" : 0
  }, {
    "name" : "ch_zaf",
    "type" : "BOOLEAN",
    "key" : false,
    "optional" : true,
    "exampleValue" : null,
    "index" : 0
  }, {
    "name" : "lai",
    "type" : "BOOLEAN",
    "key" : false,
    "optional" : true,
    "exampleValue" : null,
    "index" : 0
  }, {
    "name" : "geotherm",
    "type" : "BOOLEAN",
    "key" : false,
    "optional" : true,
    "exampleValue" : null,
    "index" : 0
  }, {
    "name" : "mining_ar",
    "type" : "BOOLEAN",
    "key" : false,
    "optional" : true,
    "exampleValue" : null,
    "index" : 0
  }, {
    "name" : "aqua_cze",
    "type" : "BOOLEAN",
    "key" : false,
    "optional" : true,
    "exampleValue" : null,
    "index" : 0
  }, {
    "name" : "can_cze",
    "type" : "BOOLEAN",
    "key" : false,
    "optional" : true,
    "exampleValue" : null,
    "index" : 0
  }, {
    "name" : "can_nor",
    "type" : "BOOLEAN",
    "key" : false,
    "optional" : true,
    "exampleValue" : null,
    "index" : 0
  }, {
    "name" : "can_col",
    "type" : "BOOLEAN",
    "key" : false,
    "optional" : true,
    "exampleValue" : null,
    "index" : 0
  }, {
    "name" : "can_vnm",
    "type" : "BOOLEAN",
    "key" : false,
    "optional" : true,
    "exampleValue" : null,
    "index" : 0
  }, {
    "name" : "can_zaf",
    "type" : "BOOLEAN",
    "key" : false,
    "optional" : true,
    "exampleValue" : null,
    "index" : 0
  }, {
    "name" : "can_grc",
    "type" : "BOOLEAN",
    "key" : false,
    "optional" : true,
    "exampleValue" : null,
    "index" : 0
  }, {
    "name" : "mari_vnm",
    "type" : "BOOLEAN",
    "key" : false,
    "optional" : true,
    "exampleValue" : null,
    "index" : 0
  }, {
    "name" : "mari_zaf",
    "type" : "BOOLEAN",
    "key" : false,
    "optional" : true,
    "exampleValue" : null,
    "index" : 0
  }, {
    "name" : "mari_nor",
    "type" : "BOOLEAN",
    "key" : false,
    "optional" : true,
    "exampleValue" : null,
    "index" : 0
  }, {
    "name" : "mari_col",
    "type" : "BOOLEAN",
    "key" : false,
    "optional" : true,
    "exampleValue" : null,
    "index" : 0
  }, {
    "name" : "mari_grc",
    "type" : "BOOLEAN",
    "key" : false,
    "optional" : true,
    "exampleValue" : null,
    "index" : 0
  }, {
    "name" : "chem_n",
    "type" : "BOOLEAN",
    "key" : false,
    "optional" : true,
    "exampleValue" : null,
    "index" : 0
  }, {
    "name" : "chem_bs",
    "type" : "BOOLEAN",
    "key" : false,
    "optional" : true,
    "exampleValue" : null,
    "index" : 0
  }, {
    "name" : "fertility",
    "type" : "BOOLEAN",
    "key" : false,
    "optional" : true,
    "exampleValue" : null,
    "index" : 0
  }, {
    "name" : "peat_thk",
    "type" : "BOOLEAN",
    "key" : false,
    "optional" : true,
    "exampleValue" : null,
    "index" : 0
  }, {
    "name" : "bulk_dens",
    "type" : "BOOLEAN",
    "key" : false,
    "optional" : true,
    "exampleValue" : null,
    "index" : 0
  }, {
    "name" : "floodpln",
    "type" : "BOOLEAN",
    "key" : false,
    "optional" : true,
    "exampleValue" : null,
    "index" : 0
  }, {
    "name" : "hydroform",
    "type" : "BOOLEAN",
    "key" : false,
    "optional" : true,
    "exampleValue" : null,
    "index" : 0
  }, {
    "name" : "hyd_meand",
    "type" : "BOOLEAN",
    "key" : false,
    "optional" : true,
    "exampleValue" : null,
    "index" : 0
  }, {
    "name" : "hma_col",
    "type" : "BOOLEAN",
    "key" : false,
    "optional" : true,
    "exampleValue" : null,
    "index" : 0
  }, {
    "name" : "hma_cze",
    "type" : "BOOLEAN",
    "key" : false,
    "optional" : true,
    "exampleValue" : null,
    "index" : 0
  }, {
    "name" : "hma_grc",
    "type" : "BOOLEAN",
    "key" : false,
    "optional" : true,
    "exampleValue" : null,
    "index" : 0
  }, {
    "name" : "hma_nor",
    "type" : "BOOLEAN",
    "key" : false,
    "optional" : true,
    "exampleValue" : null,
    "index" : 0
  }, {
    "name" : "hma_vnm",
    "type" : "BOOLEAN",
    "key" : false,
    "optional" : true,
    "exampleValue" : null,
    "index" : 0
  }, {
    "name" : "hma_zaf",
    "type" : "BOOLEAN",
    "key" : false,
    "optional" : true,
    "exampleValue" : null,
    "index" : 0
  }, {
    "name" : "occ_seas",
    "type" : "BOOLEAN",
    "key" : false,
    "optional" : true,
    "exampleValue" : null,
    "index" : 0
  }, {
    "name" : "occ_eph",
    "type" : "BOOLEAN",
    "key" : false,
    "optional" : true,
    "exampleValue" : null,
    "index" : 0
  }, {
    "name" : "occ_epi",
    "type" : "BOOLEAN",
    "key" : false,
    "optional" : true,
    "exampleValue" : null,
    "index" : 0
  }, {
    "name" : "whd_col",
    "type" : "BOOLEAN",
    "key" : false,
    "optional" : true,
    "exampleValue" : null,
    "index" : 0
  }, {
    "name" : "whd_cze",
    "type" : "BOOLEAN",
    "key" : false,
    "optional" : true,
    "exampleValue" : null,
    "index" : 0
  }, {
    "name" : "whd_grc",
    "type" : "BOOLEAN",
    "key" : false,
    "optional" : true,
    "exampleValue" : null,
    "index" : 0
  }, {
    "name" : "whd_nor",
    "type" : "BOOLEAN",
    "key" : false,
    "optional" : true,
    "exampleValue" : null,
    "index" : 0
  }, {
    "name" : "whd_vnm",
    "type" : "BOOLEAN",
    "key" : false,
    "optional" : true,
    "exampleValue" : null,
    "index" : 0
  }, {
    "name" : "whd_zaf",
    "type" : "BOOLEAN",
    "key" : false,
    "optional" : true,
    "exampleValue" : null,
    "index" : 0
  }, {
    "name" : "wsh_hier",
    "type" : "BOOLEAN",
    "key" : false,
    "optional" : true,
    "exampleValue" : null,
    "index" : 0
  }, {
    "name" : "trop_strm",
    "type" : "BOOLEAN",
    "key" : false,
    "optional" : true,
    "exampleValue" : null,
    "index" : 0
  }, {
    "name" : "coast_str",
    "type" : "BOOLEAN",
    "key" : false,
    "optional" : true,
    "exampleValue" : null,
    "index" : 0
  }, {
    "name" : "sd_temp_a",
    "type" : "BOOLEAN",
    "key" : false,
    "optional" : true,
    "exampleValue" : null,
    "index" : 0
  }, {
    "name" : "su_temp_m",
    "type" : "BOOLEAN",
    "key" : false,
    "optional" : true,
    "exampleValue" : null,
    "index" : 0
  }, {
    "name" : "wi_temp_m",
    "type" : "BOOLEAN",
    "key" : false,
    "optional" : true,
    "exampleValue" : null,
    "index" : 0
  }, {
    "name" : "sd_temp_v",
    "type" : "BOOLEAN",
    "key" : false,
    "optional" : true,
    "exampleValue" : null,
    "index" : 0
  }, {
    "name" : "tree_gr",
    "type" : "BOOLEAN",
    "key" : false,
    "optional" : true,
    "exampleValue" : null,
    "index" : 0
  }, {
    "name" : "ann_prec",
    "type" : "BOOLEAN",
    "key" : false,
    "optional" : true,
    "exampleValue" : null,
    "index" : 0
  }, {
    "name" : "ann_temp",
    "type" : "BOOLEAN",
    "key" : false,
    "optional" : true,
    "exampleValue" : null,
    "index" : 0
  }, {
    "name" : "win_wb",
    "type" : "BOOLEAN",
    "key" : false,
    "optional" : true,
    "exampleValue" : null,
    "index" : 0
  }, {
    "name" : "ann_wb",
    "type" : "BOOLEAN",
    "key" : false,
    "optional" : true,
    "exampleValue" : null,
    "index" : 0
  }, {
    "name" : "therm_blt",
    "type" : "BOOLEAN",
    "key" : false,
    "optional" : true,
    "exampleValue" : null,
    "index" : 0
  }, {
    "name" : "pin_col",
    "type" : "BOOLEAN",
    "key" : false,
    "optional" : true,
    "exampleValue" : null,
    "index" : 0
  }, {
    "name" : "new_id",
    "type" : "TEXT",
    "key" : false,
    "optional" : true,
    "exampleValue" : null,
    "index" : 0
  } ],
  "spatialExtent" : {
    "east" : 106.4932632446289,
    "west" : -75.28277587890625,
    "north" : 70.79414367675781,
    "south" : -34.66094970703125,
    "gridResolution" : null,
    "gridUnit" : null
  },
  "dependencies" : null,
  "outputs" : null,
  "categorizables" : [ ],
  "codelists" : [ ],
  "availability" : null,
  "exportFormats" : { }
}